fourwarder/batcher.py
fourwarder/config.py
fourwarder/container_handler.py
fourwarder/main.py
fourwarder/sender.py
fourwarder-0.1.0.dist-info/entry_points.txt
fourwarder-0.1.0.dist-info/WHEEL
fourwarder-0.1.0.dist-info/METADATA
fourwarder-0.1.0.dist-info/RECORD
