Metadata-Version: 2.1
Name: fourwarder
Version: 0.1.0
Summary: 
Author: Giacomo Tagliabue
Author-email: giacomo.tag@gmail.com
Requires-Python: >=3.7,<4.0
Classifier: Programming Language :: Python :: 3
Classifier: Programming Language :: Python :: 3.7
Classifier: Programming Language :: Python :: 3.8
Classifier: Programming Language :: Python :: 3.9
Requires-Dist: docker (>=5.0.2,<6.0.0)
Requires-Dist: requests (>=2.26.0,<3.0.0)
